shrinkr-0.0.1.dist-info/WHEEL
shrinkr-0.0.1.dist-info/entry_points.txt
shrinkr-0.0.1.dist-info/METADATA
shrinkr-0.0.1.dist-info/RECORD
shrinkr-0.0.1.dist-info/licenses/LICENSE
shrinkr/cli.py
shrinkr/_core.cpython-313-x86_64-linux-gnu.so
shrinkr/__init__.py
