Metadata-Version: 2.4
Name: shrinkr
Version: 0.0.1
Summary: A modular C++ compression library with Python bindings
Author: leosalgado
License-Expression: MIT
Classifier: Programming Language :: Python :: 3
Classifier: Operating System :: OS Independent
Requires-Python: >=3.11
